Workbook

Sheet How to use this
B2: Portfolio Manager - User Acceptance Testing
B3: Build 2026.08.09.11 · 188 tests across 25 areas · issued 09 August 2026
B5: What we are asking you to do
B6: Use the tool as you would in your own job, follow the tests on the 'UAT tests' sheet, and tell us what is wrong or awkward. You are not checking that we built what we said we would build. You are telling us whether it is any use.
B8: The two columns that matter most are Commentary and Feedback / improvements. A test marked Pass with an empty comment tells us almost nothing. A test marked Pass with 'worked, but I would never find this button' is worth more than the pass itself.
B10: How to record a result
B11: Result - choose from the dropdown:
B12: Pass - It did what the Expected result column says.
B13: Fail - It did not. Say what happened instead in Commentary.
B14: Blocked - You could not run it - a prerequisite failed, or you lack the role. Say which.
B15: Not applicable - The test does not apply to your role or your part of the business.
B16: Not tested - You did not get to it. Leave it rather than guessing.
... B34: Add a row to the 'Issues raised' sheet. Tests we did not think to write are the most valuable thing to come out of a UAT week.

Sheet Test accounts
A1: Test accounts and who is testing what
A2: Filled in by the administrator during section 1, then by each tester. Agree a project each before you start, so two people are not editing the same one.
A4: Tester name | B4: Email | C4: RES id | D4: Permission level (role) | E4: Additional roles | F4: Access scope | G4: Project(s) to use | H4: Areas assigned
A5: Example: A Tester | B5: a.tester@example.com | C5: RES-0103 | D5: Project Manager | E5: (none) | F5: Assigned projects | G5: PRJ-00012 | H5: 5, 6, 8
A24: The nine roles, for reference
A25: Role | B25: Default scope | C25: Permissions
A26: System Administrator | B26: Portfolio-wide | C26: 47
A27: Portfolio Manager / PMO Manager | B27: Portfolio-wide | C27: 46
A28: PMO Analyst | B28: Portfolio-wide | C28: 34
A29: Project Manager | B29: Assigned projects | C29: 29
A30: Project Sponsor / Project Lead | B30: Assigned projects | C30: 20
A31: Read-only / Auditor | B31: Selected projects | C31: 18
A32: Resource Manager / Team Manager | B32: Team projects | C32: 16
A33: Executive / Steering User | B33: Portfolio-wide | C33: 16
A34: Project Team Member | B34: Assigned projects | C34: 14

Sheet UAT tests
A1: Test ID | B1: Area | C1: Role(s) needed | D1: Prereq | E1: Test | F1: Test steps | G1: Expected result | H1: Result | I1: Commentary | J1: Feedback / improvements | K1: Tester | L1: Date
A2: SET-01 | B2: 1. Setup and accounts | C2: System Administrator | D2: - | E2: Create a test account for each role | F2: 1. Sign in as a System Administrator. 2. Open Resources. 3. For each of the nine roles, add a person (or reuse a demo person) and set their Permission level to that role. 4. Set Login status to Active and record the RES-000NN each is given. 5. Note them on the 'Test accounts' sheet of this workbook. | G2: Nine person records exist, one per role, each with a permission level and an access scope. The RES id of each is recorded.
A3: SET-02 | B3: 1. Setup and accounts | C3: System Administrator | D3: SET-01 | E3: Give each test account a sign-in | F3: 1. In the Supabase dashboard, Authentication > Users > Add user, for each tester. 2. Use their real email, invent a temporary password, tick Auto Confirm User. 3. In the SQL editor run: select public.ppm_link_person_login('their.email', 'RES-000NN'); 4. Send each tester their URL, email and temporary password. | G3: Each command returns without error. Each tester has credentials. Linking cannot be done from inside the tool, which is expected.
A4: SET-03 | B4: 1. Setup and accounts | C4: System Administrator | D4: SET-01 | E4: Set up a person with two roles | F4: 1. Open Resources and edit the Executive test account. 2. Leave Permission level as Executive / Steering User. 3. In Additional roles, select Project Sponsor / Project Lead. 4. Read the line under the picker. 5. Save. | G4: The helper line states how many roles are held and how many of the 47 permissions the combination grants. The save succeeds.
A5: SET-04 | B5: 1. Setup and accounts | C5: System Administrator | D5: SET-01 | E5: Set up the four access scopes | F5: 1. Set one tester to Portfolio-wide. 2. Set one to Assigned projects and name them as project manager on exactly two projects. 3. Set one to Team projects and give them a team that owns work. 4. Set one to Selected projects and pick exactly two projects. | G5: All four scopes are represented across the test accounts, ready for the scope tests.
A6: SET-05 | B6: 1. Setup and accounts | C6: System Administrator | D6: SET-02 | E6: Confirm nobody can change their own access | F6: 1. Sign in as a System Administrator. 2. Open Resources and edit your own record. 3. Try to change your own Permission level, Additional roles or Access scope. 4. Save. | G6: The change is refused with a message. This is enforced by the database, not just the screen, so it must fail even for an administrator.
A7: SGN-01 | B7: 2. Signing in | C7: Any | D7: SET-02 | E7: First sign-in enrols an authenticator | F7: 1. Open the tool URL in a browser that has never signed in. 2. Enter your email and the temporary password. 3. Scan the QR code with an authenticator app. 4. Enter the 6-digit code. 5. Choose your own password, at least 12 characters and different from the temporary one. | G7: You reach the tool. Neither enrolment nor the password change is asked for again.
A8: SGN-02 | B8: 2. Signing in | C8: Any | D8: SGN-01 | E8: Every later sign-in needs the authenticator code | F8: 1. Sign out. 2. Sign in with email and your own password. 3. Observe what is asked for next. | G8: A 6-digit code is required. There is no way to skip it, and no data appears until it is accepted.
A9: SGN-03 | B9: 2. Signing in | C9: Any | D9: SGN-01 | E9: A wrong authenticator code is refused clearly | F9: 1. Sign in with the correct password. 2. Enter six wrong digits. 3. Read the message. | G9: Sign-in is refused with a message naming the code as the problem. No data is shown.
A10: SGN-04 | B10: 2. Signing in | C10: Any | D10: SGN-01 | E10: A wrong password is refused clearly | F10: 1. Enter your email with a wrong password. 2. Read the message. | G10: Refused with a message that does not reveal whether the email exists.
A11: SGN-05 | B11: 2. Signing in | C11: Any | D11: SGN-01 | E11: Closing the browser signs you out | F11: 1. Sign in. 2. Close the browser completely. 3. Reopen it and go to the tool URL. | G11: You are asked to sign in again. The session is per browser session by design.
A12: SGN-06 | B12: 2. Signing in | C12: Any | D12: SGN-01 | E12: A second tab is a separate session | F12: 1. Sign in in one tab. 2. Open the tool in a second tab of the same browser. 3. Observe. | G12: The second tab asks you to sign in. Records already on screen in the first tab remain correct and complete.
A13: SGN-07 | B13: 2. Signing in | C13: System Administrator | D13: SET-02 | E13: A disabled account cannot sign in | F13: 1. As an administrator, set a tester's Login status to Disabled. 2. Ask that tester to sign in. | G13: Sign-in is refused, or succeeds but returns no data. Either is acceptable; note which happened.
... A189: ROB-05 | B189: 25. Robustness | C189: Any | D189: SGN-02 | E189: The tool behaves in a second browser | F189: 1. Repeat five core tests in a different browser, for example Edge if you used Chrome. | G189: Behaviour is the same. Record any difference and name the browser and version.

Sheet Summary
A1: UAT progress
A2: Every figure here is a formula over the 'UAT tests' sheet. It updates as testers fill it in.
A4: Overall | B4: Pass | C4: Fail | D4: Blocked | E4: Not applicable | F4: Not tested | G4: Total
A5: All areas | B5: =COUNTIF('UAT tests'!$H$2:$H$189,"Pass") -> 0 | C5: =COUNTIF('UAT tests'!$H$2:$H$189,"Fail") -> 0 | D5: =COUNTIF('UAT tests'!$H$2:$H$189,"Blocked") -> 0 | E5: =COUNTIF('UAT tests'!$H$2:$H$189,"Not applicable") -> 0 | F5: =COUNTIF('UAT tests'!$H$2:$H$189,"Not tested") -> 0 | G5: =COUNTA('UAT tests'!$A$2:$A$189) -> 188
A6: Not yet recorded | B6: =COUNTA('UAT tests'!$A$2:$A$189)-COUNTA('UAT tests'!$H$2:$H$189) -> 188
A8: By area
A9: Area | B9: Pass | C9: Fail | D9: Blocked | E9: Not applicable | F9: Not tested | G9: Tests
A10: 1. Setup and accounts | B10: =COUNTIFS('UAT tests'!$B$2:$B$189,$A10,'UAT tests'!$H$2:$H$189,"Pass") -> 0 | C10: =COUNTIFS('UAT tests'!$B$2:$B$189,$A10,'UAT tests'!$H$2:$H$189,"Fail") -> 0 | D10: =COUNTIFS('UAT tests'!$B$2:$B$189,$A10,'UAT tests'!$H$2:$H$189,"Blocked") -> 0 | E10: =COUNTIFS('UAT tests'!$B$2:$B$189,$A10,'UAT tests'!$H$2:$H$189,"Not applicable") -> 0 | F10: =COUNTIFS('UAT tests'!$B$2:$B$189,$A10,'UAT tests'!$H$2:$H$189,"Not tested") -> 0 | G10: =COUNTIF('UAT tests'!$B$2:$B$189,$A10) -> 5
A11: 2. Signing in | B11: =COUNTIFS('UAT tests'!$B$2:$B$189,$A11,'UAT tests'!$H$2:$H$189,"Pass") -> 0 | C11: =COUNTIFS('UAT tests'!$B$2:$B$189,$A11,'UAT tests'!$H$2:$H$189,"Fail") -> 0 | D11: =COUNTIFS('UAT tests'!$B$2:$B$189,$A11,'UAT tests'!$H$2:$H$189,"Blocked") -> 0 | E11: =COUNTIFS('UAT tests'!$B$2:$B$189,$A11,'UAT tests'!$H$2:$H$189,"Not applicable") -> 0 | F11: =COUNTIFS('UAT tests'!$B$2:$B$189,$A11,'UAT tests'!$H$2:$H$189,"Not tested") -> 0 | G11: =COUNTIF('UAT tests'!$B$2:$B$189,$A11) -> 9
A12: 3. Page loading and navigation | B12: =COUNTIFS('UAT tests'!$B$2:$B$189,$A12,'UAT tests'!$H$2:$H$189,"Pass") -> 0 | C12: =COUNTIFS('UAT tests'!$B$2:$B$189,$A12,'UAT tests'!$H$2:$H$189,"Fail") -> 0 | D12: =COUNTIFS('UAT tests'!$B$2:$B$189,$A12,'UAT tests'!$H$2:$H$189,"Blocked") -> 0 | E12: =COUNTIFS('UAT tests'!$B$2:$B$189,$A12,'UAT tests'!$H$2:$H$189,"Not applicable") -> 0 | F12: =COUNTIFS('UAT tests'!$B$2:$B$189,$A12,'UAT tests'!$H$2:$H$189,"Not tested") -> 0 | G12: =COUNTIF('UAT tests'!$B$2:$B$189,$A12) -> 6
A13: 4. Projects list | B13: =COUNTIFS('UAT tests'!$B$2:$B$189,$A13,'UAT tests'!$H$2:$H$189,"Pass") -> 0 | C13: =COUNTIFS('UAT tests'!$B$2:$B$189,$A13,'UAT tests'!$H$2:$H$189,"Fail") -> 0 | D13: =COUNTIFS('UAT tests'!$B$2:$B$189,$A13,'UAT tests'!$H$2:$H$189,"Blocked") -> 0 | E13: =COUNTIFS('UAT tests'!$B$2:$B$189,$A13,'UAT tests'!$H$2:$H$189,"Not applicable") -> 0 | F13: =COUNTIFS('UAT tests'!$B$2:$B$189,$A13,'UAT tests'!$H$2:$H$189,"Not tested") -> 0 | G13: =COUNTIF('UAT tests'!$B$2:$B$189,$A13) -> 10
A14: 5. Editing a project | B14: =COUNTIFS('UAT tests'!$B$2:$B$189,$A14,'UAT tests'!$H$2:$H$189,"Pass") -> 0 | C14: =COUNTIFS('UAT tests'!$B$2:$B$189,$A14,'UAT tests'!$H$2:$H$189,"Fail") -> 0 | D14: =COUNTIFS('UAT tests'!$B$2:$B$189,$A14,'UAT tests'!$H$2:$H$189,"Blocked") -> 0 | E14: =COUNTIFS('UAT tests'!$B$2:$B$189,$A14,'UAT tests'!$H$2:$H$189,"Not applicable") -> 0 | F14: =COUNTIFS('UAT tests'!$B$2:$B$189,$A14,'UAT tests'!$H$2:$H$189,"Not tested") -> 0 | G14: =COUNTIF('UAT tests'!$B$2:$B$189,$A14) -> 17
A15: 6. Project plan | B15: =COUNTIFS('UAT tests'!$B$2:$B$189,$A15,'UAT tests'!$H$2:$H$189,"Pass") -> 0 | C15: =COUNTIFS('UAT tests'!$B$2:$B$189,$A15,'UAT tests'!$H$2:$H$189,"Fail") -> 0 | D15: =COUNTIFS('UAT tests'!$B$2:$B$189,$A15,'UAT tests'!$H$2:$H$189,"Blocked") -> 0 | E15: =COUNTIFS('UAT tests'!$B$2:$B$189,$A15,'UAT tests'!$H$2:$H$189,"Not applicable") -> 0 | F15: =COUNTIFS('UAT tests'!$B$2:$B$189,$A15,'UAT tests'!$H$2:$H$189,"Not tested") -> 0 | G15: =COUNTIF('UAT tests'!$B$2:$B$189,$A15) -> 13
A16: 7. Milestones | B16: =COUNTIFS('UAT tests'!$B$2:$B$189,$A16,'UAT tests'!$H$2:$H$189,"Pass") -> 0 | C16: =COUNTIFS('UAT tests'!$B$2:$B$189,$A16,'UAT tests'!$H$2:$H$189,"Fail") -> 0 | D16: =COUNTIFS('UAT tests'!$B$2:$B$189,$A16,'UAT tests'!$H$2:$H$189,"Blocked") -> 0 | E16: =COUNTIFS('UAT tests'!$B$2:$B$189,$A16,'UAT tests'!$H$2:$H$189,"Not applicable") -> 0 | F16: =COUNTIFS('UAT tests'!$B$2:$B$189,$A16,'UAT tests'!$H$2:$H$189,"Not tested") -> 0 | G16: =COUNTIF('UAT tests'!$B$2:$B$189,$A16) -> 4
A17: 8. Stage gates | B17: =COUNTIFS('UAT tests'!$B$2:$B$189,$A17,'UAT tests'!$H$2:$H$189,"Pass") -> 0 | C17: =COUNTIFS('UAT tests'!$B$2:$B$189,$A17,'UAT tests'!$H$2:$H$189,"Fail") -> 0 | D17: =COUNTIFS('UAT tests'!$B$2:$B$189,$A17,'UAT tests'!$H$2:$H$189,"Blocked") -> 0 | E17: =COUNTIFS('UAT tests'!$B$2:$B$189,$A17,'UAT tests'!$H$2:$H$189,"Not applicable") -> 0 | F17: =COUNTIFS('UAT tests'!$B$2:$B$189,$A17,'UAT tests'!$H$2:$H$189,"Not tested") -> 0 | G17: =COUNTIF('UAT tests'!$B$2:$B$189,$A17) -> 10
A18: 9. RAID log | B18: =COUNTIFS('UAT tests'!$B$2:$B$189,$A18,'UAT tests'!$H$2:$H$189,"Pass") -> 0 | C18: =COUNTIFS('UAT tests'!$B$2:$B$189,$A18,'UAT tests'!$H$2:$H$189,"Fail") -> 0 | D18: =COUNTIFS('UAT tests'!$B$2:$B$189,$A18,'UAT tests'!$H$2:$H$189,"Blocked") -> 0 | E18: =COUNTIFS('UAT tests'!$B$2:$B$189,$A18,'UAT tests'!$H$2:$H$189,"Not applicable") -> 0 | F18: =COUNTIFS('UAT tests'!$B$2:$B$189,$A18,'UAT tests'!$H$2:$H$189,"Not tested") -> 0 | G18: =COUNTIF('UAT tests'!$B$2:$B$189,$A18) -> 7
A19: 10. Registers | B19: =COUNTIFS('UAT tests'!$B$2:$B$189,$A19,'UAT tests'!$H$2:$H$189,"Pass") -> 0 | C19: =COUNTIFS('UAT tests'!$B$2:$B$189,$A19,'UAT tests'!$H$2:$H$189,"Fail") -> 0 | D19: =COUNTIFS('UAT tests'!$B$2:$B$189,$A19,'UAT tests'!$H$2:$H$189,"Blocked") -> 0 | E19: =COUNTIFS('UAT tests'!$B$2:$B$189,$A19,'UAT tests'!$H$2:$H$189,"Not applicable") -> 0 | F19: =COUNTIFS('UAT tests'!$B$2:$B$189,$A19,'UAT tests'!$H$2:$H$189,"Not tested") -> 0 | G19: =COUNTIF('UAT tests'!$B$2:$B$189,$A19) -> 7
A20: 11. Benefits | B20: =COUNTIFS('UAT tests'!$B$2:$B$189,$A20,'UAT tests'!$H$2:$H$189,"Pass") -> 0 | C20: =COUNTIFS('UAT tests'!$B$2:$B$189,$A20,'UAT tests'!$H$2:$H$189,"Fail") -> 0 | D20: =COUNTIFS('UAT tests'!$B$2:$B$189,$A20,'UAT tests'!$H$2:$H$189,"Blocked") -> 0 | E20: =COUNTIFS('UAT tests'!$B$2:$B$189,$A20,'UAT tests'!$H$2:$H$189,"Not applicable") -> 0 | F20: =COUNTIFS('UAT tests'!$B$2:$B$189,$A20,'UAT tests'!$H$2:$H$189,"Not tested") -> 0 | G20: =COUNTIF('UAT tests'!$B$2:$B$189,$A20) -> 3
A21: 12. Financials | B21: =COUNTIFS('UAT tests'!$B$2:$B$189,$A21,'UAT tests'!$H$2:$H$189,"Pass") -> 0 | C21: =COUNTIFS('UAT tests'!$B$2:$B$189,$A21,'UAT tests'!$H$2:$H$189,"Fail") -> 0 | D21: =COUNTIFS('UAT tests'!$B$2:$B$189,$A21,'UAT tests'!$H$2:$H$189,"Blocked") -> 0 | E21: =COUNTIFS('UAT tests'!$B$2:$B$189,$A21,'UAT tests'!$H$2:$H$189,"Not applicable") -> 0 | F21: =COUNTIFS('UAT tests'!$B$2:$B$189,$A21,'UAT tests'!$H$2:$H$189,"Not tested") -> 0 | G21: =COUNTIF('UAT tests'!$B$2:$B$189,$A21) -> 8
... A34: 25. Robustness | B34: =COUNTIFS('UAT tests'!$B$2:$B$189,$A34,'UAT tests'!$H$2:$H$189,"Pass") -> 0 | C34: =COUNTIFS('UAT tests'!$B$2:$B$189,$A34,'UAT tests'!$H$2:$H$189,"Fail") -> 0 | D34: =COUNTIFS('UAT tests'!$B$2:$B$189,$A34,'UAT tests'!$H$2:$H$189,"Blocked") -> 0 | E34: =COUNTIFS('UAT tests'!$B$2:$B$189,$A34,'UAT tests'!$H$2:$H$189,"Not applicable") -> 0 | F34: =COUNTIFS('UAT tests'!$B$2:$B$189,$A34,'UAT tests'!$H$2:$H$189,"Not tested") -> 0 | G34: =COUNTIF('UAT tests'!$B$2:$B$189,$A34) -> 5
A37: What to do with this
A38: · Any Fail is a defect. Read its Commentary before deciding severity - some will be wording, some will be data loss.
A39: · Any Blocked means a prerequisite failed. Fix the prerequisite before re-running the section.
A40: · Read every Feedback cell, including the ones on tests that passed. That is where the design changes come from.
A41: · Areas 20 and 21 (roles and scopes) are the ones to take most seriously: getting those wrong shows somebody data they should not see.

Sheet Issues raised
A1: Anything you found that is not on the test list
A2: Tests we did not think to write are the most valuable thing to come out of a UAT week. One row per issue.
A4: # | B4: Raised by | C4: Date | D4: Page | E4: Role you were using | F4: What happened | G4: What you expected | H4: How to reproduce it | I4: Severity | J4: Console error (F12), if any
A5: 1 | B5: A Tester | D5: Project plan | E5: Project Manager | F5: The timeline drew bars a week late at Quarter zoom | G5: Bars aligned to the dates in the table | H5: Open PRJ-00012 plan, switch zoom to Quarter | I5: Wrong data
